quiz_app/__init__.py
quizofit-0.1.0.dist-info/METADATA
quizofit-0.1.0.dist-info/WHEEL
quizofit-0.1.0.dist-info/RECORD
