Metadata-Version: 2.1
Name: quizofit
Version: 0.1.0
Summary: A Quiz App. Make a quiz out of stuff
Author: Geir Arne Hjelle
Author-email: geirarne@realpython.com
Maintainer: Robert Portelli
Maintainer-email: github@robertportelli.com
Requires-Python: >=3.11,<4.0
Classifier: Programming Language :: Python :: 3
Classifier: Programming Language :: Python :: 3.11
